PyPDF2/__init__.py
PyPDF2/_cmap.py
PyPDF2/_encryption.py
PyPDF2/_merger.py
PyPDF2/_page.py
PyPDF2/_reader.py
PyPDF2/_security.py
PyPDF2/_utils.py
PyPDF2/_version.py
PyPDF2/_writer.py
PyPDF2/constants.py
PyPDF2/errors.py
PyPDF2/filters.py
PyPDF2/generic.py
PyPDF2/pagerange.py
PyPDF2/papersizes.py
PyPDF2/py.typed
PyPDF2/types.py
PyPDF2/xmp.py
PyPDF2/_codecs/__init__.py
PyPDF2/_codecs/adobe_glyphs.py
PyPDF2/_codecs/pdfdoc.py
PyPDF2/_codecs/std.py
PyPDF2/_codecs/symbol.py
PyPDF2/_codecs/zapfding.py
PyPDF2-2.7.0.dist-info/LICENSE
PyPDF2-2.7.0.dist-info/METADATA
PyPDF2-2.7.0.dist-info/WHEEL
PyPDF2-2.7.0.dist-info/top_level.txt
PyPDF2-2.7.0.dist-info/RECORD
