Metadata-Version: 2.1
Name: PyPDF2
Version: 2.7.0
Summary: A pure-python PDF library capable of splitting, merging, cropping, and transforming PDF files
Home-page: https://pypdf2.readthedocs.io/en/latest/
Author: Mathieu Fenniak
Author-email: biziqe@mathieu.fenniak.net
Maintainer: Martin Thoma
Maintainer-email: info@martin-thoma.de
License: BSD-3-Clause
Project-URL: Source, https://github.com/py-pdf/PyPDF2
Project-URL: Bug Reports, https://github.com/py-pdf/PyPDF2/issues
Project-URL: Changelog, https://raw.githubusercontent.com/py-pdf/PyPDF2/main/CHANGELOG
Platform: UNKNOWN
Classifier: Development Status :: 5 - Production/Stable
Classifier: Intended Audience :: Developers
Classifier: License :: OSI Approved :: BSD License
Classifier: Programming Language :: Python :: 3
Classifier: Programming Language :: Python :: 3.6
Classifier: Programming Language :: Python :: 3.7
Classifier: Programming Language :: Python :: 3.8
Classifier: Programming Language :: Python :: 3.9
Classifier: Programming Language :: Python :: 3.10
Classifier: Operating System :: OS Independent
Classifier: Topic :: Software Development :: Libraries :: Python Modules
Classifier: Typing :: Typed
Requires-Python: >=3.6
Provides-Extra: crypto
